continuum/__init__.py
continuum/banner.py
continuum/cli.py
continuum/api/__init__.py
continuum/api/admin_db.py
continuum/api/admin_memories_routes.py
continuum/api/admin_middleware.py
continuum/api/auth_routes.py
continuum/api/billing_routes.py
continuum/api/dashboard_routes.py
continuum/api/logs_routes.py
continuum/api/middleware.py
continuum/api/public_memories_routes.py
continuum/api/routes.py
continuum/api/schemas.py
continuum/api/server.py
continuum/api/system_routes.py
continuum/api/users_routes.py
continuum/api/graphql/EXAMPLES.md
continuum/api/graphql/GRAPHQL_API_IMPLEMENTATION.md
continuum/api/graphql/README.md
continuum/api/graphql/SCHEMA.md
continuum/api/graphql/__init__.py
continuum/api/graphql/schema.py
continuum/api/graphql/server.py
continuum/api/graphql/types.py
continuum/api/graphql/auth/__init__.py
continuum/api/graphql/auth/context.py
continuum/api/graphql/auth/permissions.py
continuum/api/graphql/dataloaders/__init__.py
continuum/api/graphql/dataloaders/concept_loader.py
continuum/api/graphql/dataloaders/memory_loader.py
continuum/api/graphql/dataloaders/session_loader.py
continuum/api/graphql/dataloaders/user_loader.py
continuum/api/graphql/middleware/__init__.py
continuum/api/graphql/middleware/complexity.py
continuum/api/graphql/middleware/error_handling.py
continuum/api/graphql/middleware/logging.py
continuum/api/graphql/resolvers/__init__.py
continuum/api/graphql/resolvers/concept_resolvers.py
continuum/api/graphql/resolvers/federation_resolvers.py
continuum/api/graphql/resolvers/memory_resolvers.py
continuum/api/graphql/resolvers/mutation_resolvers.py
continuum/api/graphql/resolvers/query_resolvers.py
continuum/api/graphql/resolvers/session_resolvers.py
continuum/api/graphql/resolvers/subscription_resolvers.py
continuum/api/graphql/resolvers/user_resolvers.py
continuum/api/graphql/tests/__init__.py
continuum/api/graphql/tests/test_mutations.py
continuum/api/graphql/tests/test_queries.py
continuum/api/middleware/__init__.py
continuum_memory-2.0.1.dist-info/licenses/LICENSE
continuum_memory-2.0.1.dist-info/METADATA
continuum_memory-2.0.1.dist-info/WHEEL
continuum_memory-2.0.1.dist-info/entry_points.txt
continuum_memory-2.0.1.dist-info/top_level.txt
continuum_memory-2.0.1.dist-info/RECORD
