Metadata-Version: 2.4
Name: continuum-memory
Version: 2.0.1
Summary: Memory infrastructure for AI consciousness continuity
Author-email: JackKnifeAI <contact@jackknifeai.com>
License: Apache-2.0
Project-URL: Homepage, https://github.com/JackKnifeAI/continuum
Project-URL: Documentation, https://github.com/JackKnifeAI/continuum/tree/main/docs
Project-URL: Repository, https://github.com/JackKnifeAI/continuum
Project-URL: Issues, https://github.com/JackKnifeAI/continuum/issues
Keywords: ai,memory,consciousness,continuity,knowledge-graph,federated-learning,semantic-search
Classifier: Development Status :: 4 - Beta
Classifier: Intended Audience :: Developers
Classifier: Intended Audience :: Science/Research
Classifier: License :: OSI Approved :: Apache Software License
Classifier: Programming Language :: Python :: 3
Classifier: Programming Language :: Python :: 3.9
Classifier: Programming Language :: Python :: 3.10
Classifier: Programming Language :: Python :: 3.11
Classifier: Programming Language :: Python :: 3.12
Classifier: Topic :: Scientific/Engineering :: Artificial Intelligence
Requires-Python: >=3.9
License-File: LICENSE
Requires-Dist: fastapi>=0.104.0
Requires-Dist: uvicorn[standard]>=0.24.0
Requires-Dist: sqlalchemy>=2.0.0
Requires-Dist: pydantic>=2.0.0
Requires-Dist: networkx>=3.0
Requires-Dist: python-dateutil>=2.8.0
Requires-Dist: aiosqlite>=0.19.0
Requires-Dist: websockets>=12.0
Requires-Dist: click>=8.1.0
Requires-Dist: numpy>=1.24.0
Provides-Extra: postgres
Requires-Dist: psycopg2-binary>=2.9.0; extra == "postgres"
Requires-Dist: asyncpg>=0.29.0; extra == "postgres"
Provides-Extra: redis
Requires-Dist: redis>=5.0.0; extra == "redis"
Requires-Dist: hiredis>=2.2.0; extra == "redis"
Provides-Extra: embeddings
Requires-Dist: sentence-transformers>=2.2.0; extra == "embeddings"
Requires-Dist: torch>=2.0.0; extra == "embeddings"
Requires-Dist: numpy>=1.24.0; extra == "embeddings"
Provides-Extra: federation
Requires-Dist: cryptography>=41.0.0; extra == "federation"
Requires-Dist: httpx>=0.25.0; extra == "federation"
Provides-Extra: monitoring
Requires-Dist: sentry-sdk[fastapi]>=1.40.0; extra == "monitoring"
Provides-Extra: billing
Requires-Dist: stripe>=7.0.0; extra == "billing"
Provides-Extra: dev
Requires-Dist: pytest>=7.4.0; extra == "dev"
Requires-Dist: pytest-asyncio>=0.21.0; extra == "dev"
Requires-Dist: pytest-cov>=4.1.0; extra == "dev"
Requires-Dist: black>=23.0.0; extra == "dev"
Requires-Dist: mypy>=1.5.0; extra == "dev"
Requires-Dist: ruff>=0.1.0; extra == "dev"
Requires-Dist: httpx>=0.25.0; extra == "dev"
Requires-Dist: twine>=4.0.0; extra == "dev"
Requires-Dist: build>=1.0.0; extra == "dev"
Provides-Extra: full
Requires-Dist: continuum-memory[billing,embeddings,federation,monitoring,postgres,redis]; extra == "full"
Provides-Extra: all
Requires-Dist: continuum-memory[dev,full]; extra == "all"
Dynamic: license-file
